{
    "total": [
        {
            "id": "100004366982560",
            "count": 0
        },
        {
            "id": "61569338451417",
            "count": 0
        },
        {
            "id": "61563496809381",
            "count": 78
        },
        {
            "id": "61577050643994",
            "count": 0
        },
        {
            "id": "100091313000090",
            "count": 0
        },
        {
            "id": "100068861768111",
            "count": 0
        },
        {
            "id": "100080152698087",
            "count": 0
        },
        {
            "id": "100090518522825",
            "count": 0
        },
        {
            "id": "61569795707805",
            "count": 0
        },
        {
            "id": "61557751285756",
            "count": 0
        },
        {
            "id": "61563801070353",
            "count": 0
        },
        {
            "id": "61550807512404",
            "count": 0
        },
        {
            "id": "61556139488045",
            "count": 0
        },
        {
            "id": "61550951499471",
            "count": 0
        },
        {
            "id": "100003400690051",
            "count": 0
        },
        {
            "id": "100086620849345",
            "count": 0
        },
        {
            "id": "100091769754934",
            "count": 0
        },
        {
            "id": "61562564625370",
            "count": 0
        },
        {
            "id": "100075476904971",
            "count": 0
        },
        {
            "id": "61554085977198",
            "count": 0
        },
        {
            "id": "61576303087087",
            "count": 0
        },
        {
            "id": "100090183633143",
            "count": 0
        },
        {
            "id": "100064900510879",
            "count": 0
        },
        {
            "id": "100088856464252",
            "count": 0
        },
        {
            "id": "100064836047753",
            "count": 0
        },
        {
            "id": "100075241353285",
            "count": 7
        },
        {
            "id": "100093035131692",
            "count": 2
        },
        {
            "id": "61555812975932",
            "count": 0
        },
        {
            "id": "61555315402231",
            "count": 26
        },
        {
            "id": "100067074994636",
            "count": 4
        },
        {
            "id": "100016721569402",
            "count": 0
        },
        {
            "id": "100072621417020",
            "count": 0
        },
        {
            "id": "100036907965091",
            "count": 0
        },
        {
            "id": "100078738729314",
            "count": 0
        },
        {
            "id": "61576808576607",
            "count": 0
        },
        {
            "id": "61566315946205",
            "count": 0
        },
        {
            "id": "61573134763751",
            "count": 0
        },
        {
            "id": "100094266671898",
            "count": 0
        },
        {
            "id": "100091827653492",
            "count": 0
        },
        {
            "id": "100069413591161",
            "count": 2
        },
        {
            "id": "61571179656820",
            "count": 0
        },
        {
            "id": "100084053954585",
            "count": 0
        },
        {
            "id": "61565926051279",
            "count": 0
        },
        {
            "id": "61575653644435",
            "count": 0
        },
        {
            "id": "61559687282718",
            "count": 0
        },
        {
            "id": "100093260420505",
            "count": 0
        },
        {
            "id": "100088184953277",
            "count": 0
        },
        {
            "id": "100046491823260",
            "count": 0
        },
        {
            "id": "61551598754384",
            "count": 0
        },
        {
            "id": "100078074537976",
            "count": 0
        },
        {
            "id": "61576748741913",
            "count": 0
        },
        {
            "id": "61565416546012",
            "count": 0
        },
        {
            "id": "61572605409468",
            "count": 0
        },
        {
            "id": "100089484682790",
            "count": 0
        },
        {
            "id": "61563816474622",
            "count": 0
        },
        {
            "id": "100054238185744",
            "count": 0
        },
        {
            "id": "100087502185841",
            "count": 0
        },
        {
            "id": "100023417120542",
            "count": 3
        },
        {
            "id": "100080987002074",
            "count": 0
        },
        {
            "id": "100061767325182",
            "count": 1
        },
        {
            "id": "100052091616457",
            "count": 0
        },
        {
            "id": "61570942973518",
            "count": 0
        },
        {
            "id": "100095167591736",
            "count": 5
        },
        {
            "id": "61563371807835",
            "count": 0
        },
        {
            "id": "61572794682692",
            "count": 0
        },
        {
            "id": "100049794199395",
            "count": 0
        },
        {
            "id": "1159830790",
            "count": 0
        },
        {
            "id": "100076389226937",
            "count": 0
        },
        {
            "id": "61557186861552",
            "count": 0
        },
        {
            "id": "100076319085100",
            "count": 14
        },
        {
            "id": "61575275421167",
            "count": 0
        },
        {
            "id": "100093316167658",
            "count": 0
        },
        {
            "id": "61568101333346",
            "count": 0
        },
        {
            "id": "61567137231981",
            "count": 12
        },
        {
            "id": "61556420127089",
            "count": 0
        },
        {
            "id": "100095460641478",
            "count": 0
        },
        {
            "id": "61568278007683",
            "count": 73
        },
        {
            "id": "61564167278498",
            "count": 35
        },
        {
            "id": "100027455436738",
            "count": 0
        },
        {
            "id": "100082900982212",
            "count": 0
        },
        {
            "id": "100094512588578",
            "count": 0
        },
        {
            "id": "61572591704444",
            "count": 0
        },
        {
            "id": "100060204365790",
            "count": 0
        },
        {
            "id": "100074496522992",
            "count": 0
        },
        {
            "id": "61576283133154",
            "count": 0
        },
        {
            "id": "100094054120969",
            "count": 3
        },
        {
            "id": "100087347266718",
            "count": 0
        },
        {
            "id": "61550856910712",
            "count": 0
        },
        {
            "id": "100049598619114",
            "count": 0
        },
        {
            "id": "100024191822441",
            "count": 0
        },
        {
            "id": "100072570150185",
            "count": 0
        },
        {
            "id": "61571018824787",
            "count": 0
        },
        {
            "id": "100091887677635",
            "count": 0
        },
        {
            "id": "61559795476222",
            "count": 0
        },
        {
            "id": "61550974984898",
            "count": 0
        },
        {
            "id": "61558254400327",
            "count": 0
        },
        {
            "id": "61577376624706",
            "count": 0
        },
        {
            "id": "61558260482380",
            "count": 0
        },
        {
            "id": "61575080083211",
            "count": 0
        },
        {
            "id": "706632570",
            "count": 0
        },
        {
            "id": "100077086391543",
            "count": 0
        },
        {
            "id": "61564917430103",
            "count": 0
        },
        {
            "id": "61574897218707",
            "count": 104
        },
        {
            "id": "61577384667474",
            "count": 0
        },
        {
            "id": "61577399547420",
            "count": 0
        },
        {
            "id": "100068760339372",
            "count": 0
        },
        {
            "id": "61575964492920",
            "count": 0
        },
        {
            "id": "61554796626113",
            "count": 0
        },
        {
            "id": "61565430903608",
            "count": 0
        },
        {
            "id": "61566324585655",
            "count": 0
        },
        {
            "id": "61563081494832",
            "count": 9
        },
        {
            "id": "61563338433154",
            "count": 0
        },
        {
            "id": "61577350772075",
            "count": 0
        },
        {
            "id": "100041071671685",
            "count": 1
        },
        {
            "id": "61574196725988",
            "count": 0
        },
        {
            "id": "61566302851089",
            "count": 1
        },
        {
            "id": "100004204689863",
            "count": 0
        },
        {
            "id": "100080665522298",
            "count": 0
        },
        {
            "id": "61571461029115",
            "count": 0
        },
        {
            "id": "61555109330415",
            "count": 0
        },
        {
            "id": "61554427572388",
            "count": 0
        },
        {
            "id": "61573176244352",
            "count": 0
        },
        {
            "id": "100001664242548",
            "count": 0
        },
        {
            "id": "100079781445543",
            "count": 0
        },
        {
            "id": "61577473147128",
            "count": 0
        },
        {
            "id": "61559388620470",
            "count": 0
        },
        {
            "id": "100050335652391",
            "count": 0
        },
        {
            "id": "61576322793220",
            "count": 2
        },
        {
            "id": "61560437371885",
            "count": 0
        },
        {
            "id": "100079756907572",
            "count": 0
        },
        {
            "id": "61575619948093",
            "count": 0
        },
        {
            "id": "61570064048722",
            "count": 0
        },
        {
            "id": "61576593236518",
            "count": 0
        },
        {
            "id": "61572692185146",
            "count": 0
        },
        {
            "id": "61573015991517",
            "count": 0
        },
        {
            "id": "61577338381895",
            "count": 0
        },
        {
            "id": "61573057942187",
            "count": 5
        },
        {
            "id": "100054255814951",
            "count": 0
        },
        {
            "id": "61575859743375",
            "count": 2
        },
        {
            "id": "61556365787922",
            "count": 35
        },
        {
            "id": "61570065247432",
            "count": 0
        },
        {
            "id": "61567036355819",
            "count": 0
        },
        {
            "id": "100089877112021",
            "count": 0
        },
        {
            "id": "61561301781412",
            "count": 0
        },
        {
            "id": "61569508901773",
            "count": 0
        },
        {
            "id": "100095363102708",
            "count": 0
        },
        {
            "id": "61555318124009",
            "count": 2
        },
        {
            "id": "100072003416462",
            "count": 23
        },
        {
            "id": "61577324252460",
            "count": 13
        },
        {
            "id": "100075416601396",
            "count": 12
        },
        {
            "id": "100093017079432",
            "count": 1
        },
        {
            "id": "100033622700609",
            "count": 87
        },
        {
            "id": "61559800701404",
            "count": 9
        },
        {
            "id": "100054549946196",
            "count": 0
        },
        {
            "id": "61573785396957",
            "count": 15
        },
        {
            "id": "100073454930514",
            "count": 0
        },
        {
            "id": "100071847031894",
            "count": 0
        },
        {
            "id": "61576818456790",
            "count": 0
        },
        {
            "id": "100051958717970",
            "count": 37
        },
        {
            "id": "61577423374306",
            "count": 5
        },
        {
            "id": "61567376367950",
            "count": 0
        },
        {
            "id": "61577774257596",
            "count": 2
        },
        {
            "id": "61556472763954",
            "count": 0
        },
        {
            "id": "61573424942469",
            "count": 1
        }
    ],
    "week": [
        {
            "id": "100004366982560",
            "count": 0
        },
        {
            "id": "61569338451417",
            "count": 0
        },
        {
            "id": "61563496809381",
            "count": 78
        },
        {
            "id": "61577050643994",
            "count": 0
        },
        {
            "id": "100091313000090",
            "count": 0
        },
        {
            "id": "100068861768111",
            "count": 0
        },
        {
            "id": "100080152698087",
            "count": 0
        },
        {
            "id": "100090518522825",
            "count": 0
        },
        {
            "id": "61569795707805",
            "count": 0
        },
        {
            "id": "61557751285756",
            "count": 0
        },
        {
            "id": "61563801070353",
            "count": 0
        },
        {
            "id": "61550807512404",
            "count": 0
        },
        {
            "id": "61556139488045",
            "count": 0
        },
        {
            "id": "61550951499471",
            "count": 0
        },
        {
            "id": "100003400690051",
            "count": 0
        },
        {
            "id": "100086620849345",
            "count": 0
        },
        {
            "id": "100091769754934",
            "count": 0
        },
        {
            "id": "61562564625370",
            "count": 0
        },
        {
            "id": "100075476904971",
            "count": 0
        },
        {
            "id": "61554085977198",
            "count": 0
        },
        {
            "id": "61576303087087",
            "count": 0
        },
        {
            "id": "100090183633143",
            "count": 0
        },
        {
            "id": "100064900510879",
            "count": 0
        },
        {
            "id": "100088856464252",
            "count": 0
        },
        {
            "id": "100064836047753",
            "count": 0
        },
        {
            "id": "100075241353285",
            "count": 7
        },
        {
            "id": "100093035131692",
            "count": 2
        },
        {
            "id": "61555812975932",
            "count": 0
        },
        {
            "id": "61555315402231",
            "count": 26
        },
        {
            "id": "100067074994636",
            "count": 4
        },
        {
            "id": "100016721569402",
            "count": 0
        },
        {
            "id": "100072621417020",
            "count": 0
        },
        {
            "id": "100036907965091",
            "count": 0
        },
        {
            "id": "100078738729314",
            "count": 0
        },
        {
            "id": "61576808576607",
            "count": 0
        },
        {
            "id": "61566315946205",
            "count": 0
        },
        {
            "id": "61573134763751",
            "count": 0
        },
        {
            "id": "100094266671898",
            "count": 0
        },
        {
            "id": "100091827653492",
            "count": 0
        },
        {
            "id": "100069413591161",
            "count": 2
        },
        {
            "id": "61571179656820",
            "count": 0
        },
        {
            "id": "100084053954585",
            "count": 0
        },
        {
            "id": "61565926051279",
            "count": 0
        },
        {
            "id": "61575653644435",
            "count": 0
        },
        {
            "id": "61559687282718",
            "count": 0
        },
        {
            "id": "100093260420505",
            "count": 0
        },
        {
            "id": "100088184953277",
            "count": 0
        },
        {
            "id": "100046491823260",
            "count": 0
        },
        {
            "id": "61551598754384",
            "count": 0
        },
        {
            "id": "100078074537976",
            "count": 0
        },
        {
            "id": "61576748741913",
            "count": 0
        },
        {
            "id": "61565416546012",
            "count": 0
        },
        {
            "id": "61572605409468",
            "count": 0
        },
        {
            "id": "100089484682790",
            "count": 0
        },
        {
            "id": "61563816474622",
            "count": 0
        },
        {
            "id": "100054238185744",
            "count": 0
        },
        {
            "id": "100087502185841",
            "count": 0
        },
        {
            "id": "100023417120542",
            "count": 3
        },
        {
            "id": "100080987002074",
            "count": 0
        },
        {
            "id": "100061767325182",
            "count": 1
        },
        {
            "id": "100052091616457",
            "count": 0
        },
        {
            "id": "61570942973518",
            "count": 0
        },
        {
            "id": "100095167591736",
            "count": 5
        },
        {
            "id": "61563371807835",
            "count": 0
        },
        {
            "id": "61572794682692",
            "count": 0
        },
        {
            "id": "100049794199395",
            "count": 0
        },
        {
            "id": "1159830790",
            "count": 0
        },
        {
            "id": "100076389226937",
            "count": 0
        },
        {
            "id": "61557186861552",
            "count": 0
        },
        {
            "id": "100076319085100",
            "count": 14
        },
        {
            "id": "61575275421167",
            "count": 0
        },
        {
            "id": "100093316167658",
            "count": 0
        },
        {
            "id": "61568101333346",
            "count": 0
        },
        {
            "id": "61567137231981",
            "count": 12
        },
        {
            "id": "61556420127089",
            "count": 0
        },
        {
            "id": "100095460641478",
            "count": 0
        },
        {
            "id": "61568278007683",
            "count": 73
        },
        {
            "id": "61564167278498",
            "count": 35
        },
        {
            "id": "100027455436738",
            "count": 0
        },
        {
            "id": "100082900982212",
            "count": 0
        },
        {
            "id": "100094512588578",
            "count": 0
        },
        {
            "id": "61572591704444",
            "count": 0
        },
        {
            "id": "100060204365790",
            "count": 0
        },
        {
            "id": "100074496522992",
            "count": 0
        },
        {
            "id": "61576283133154",
            "count": 0
        },
        {
            "id": "100094054120969",
            "count": 3
        },
        {
            "id": "100087347266718",
            "count": 0
        },
        {
            "id": "61550856910712",
            "count": 0
        },
        {
            "id": "100049598619114",
            "count": 0
        },
        {
            "id": "100024191822441",
            "count": 0
        },
        {
            "id": "100072570150185",
            "count": 0
        },
        {
            "id": "61571018824787",
            "count": 0
        },
        {
            "id": "100091887677635",
            "count": 0
        },
        {
            "id": "61559795476222",
            "count": 0
        },
        {
            "id": "61550974984898",
            "count": 0
        },
        {
            "id": "61558254400327",
            "count": 0
        },
        {
            "id": "61577376624706",
            "count": 0
        },
        {
            "id": "61558260482380",
            "count": 0
        },
        {
            "id": "61575080083211",
            "count": 0
        },
        {
            "id": "706632570",
            "count": 0
        },
        {
            "id": "100077086391543",
            "count": 0
        },
        {
            "id": "61564917430103",
            "count": 0
        },
        {
            "id": "61574897218707",
            "count": 104
        },
        {
            "id": "61577384667474",
            "count": 0
        },
        {
            "id": "61577399547420",
            "count": 0
        },
        {
            "id": "100068760339372",
            "count": 0
        },
        {
            "id": "61575964492920",
            "count": 0
        },
        {
            "id": "61554796626113",
            "count": 0
        },
        {
            "id": "61565430903608",
            "count": 0
        },
        {
            "id": "61566324585655",
            "count": 0
        },
        {
            "id": "61563081494832",
            "count": 9
        },
        {
            "id": "61563338433154",
            "count": 0
        },
        {
            "id": "61577350772075",
            "count": 0
        },
        {
            "id": "100041071671685",
            "count": 1
        },
        {
            "id": "61574196725988",
            "count": 0
        },
        {
            "id": "61566302851089",
            "count": 1
        },
        {
            "id": "100004204689863",
            "count": 0
        },
        {
            "id": "100080665522298",
            "count": 0
        },
        {
            "id": "61571461029115",
            "count": 0
        },
        {
            "id": "61555109330415",
            "count": 0
        },
        {
            "id": "61554427572388",
            "count": 0
        },
        {
            "id": "61573176244352",
            "count": 0
        },
        {
            "id": "100001664242548",
            "count": 0
        },
        {
            "id": "100079781445543",
            "count": 0
        },
        {
            "id": "61577473147128",
            "count": 0
        },
        {
            "id": "61559388620470",
            "count": 0
        },
        {
            "id": "100050335652391",
            "count": 0
        },
        {
            "id": "61576322793220",
            "count": 2
        },
        {
            "id": "61560437371885",
            "count": 0
        },
        {
            "id": "100079756907572",
            "count": 0
        },
        {
            "id": "61575619948093",
            "count": 0
        },
        {
            "id": "61570064048722",
            "count": 0
        },
        {
            "id": "61576593236518",
            "count": 0
        },
        {
            "id": "61572692185146",
            "count": 0
        },
        {
            "id": "61573015991517",
            "count": 0
        },
        {
            "id": "61577338381895",
            "count": 0
        },
        {
            "id": "61573057942187",
            "count": 5
        },
        {
            "id": "100054255814951",
            "count": 0
        },
        {
            "id": "61575859743375",
            "count": 2
        },
        {
            "id": "61556365787922",
            "count": 35
        },
        {
            "id": "61570065247432",
            "count": 0
        },
        {
            "id": "61567036355819",
            "count": 0
        },
        {
            "id": "100089877112021",
            "count": 0
        },
        {
            "id": "61561301781412",
            "count": 0
        },
        {
            "id": "61569508901773",
            "count": 0
        },
        {
            "id": "100095363102708",
            "count": 0
        },
        {
            "id": "61555318124009",
            "count": 2
        },
        {
            "id": "100072003416462",
            "count": 23
        },
        {
            "id": "61577324252460",
            "count": 13
        },
        {
            "id": "100075416601396",
            "count": 12
        },
        {
            "id": "100093017079432",
            "count": 1
        },
        {
            "id": "100033622700609",
            "count": 87
        },
        {
            "id": "61559800701404",
            "count": 9
        },
        {
            "id": "100054549946196",
            "count": 0
        },
        {
            "id": "61573785396957",
            "count": 15
        },
        {
            "id": "100073454930514",
            "count": 0
        },
        {
            "id": "100071847031894",
            "count": 0
        },
        {
            "id": "61576818456790",
            "count": 0
        },
        {
            "id": "100051958717970",
            "count": 37
        },
        {
            "id": "61577423374306",
            "count": 5
        },
        {
            "id": "61567376367950",
            "count": 0
        },
        {
            "id": "61577774257596",
            "count": 2
        },
        {
            "id": "61556472763954",
            "count": 0
        },
        {
            "id": "61573424942469",
            "count": 1
        }
    ],
    "day": [
        {
            "id": "100004366982560",
            "count": 0
        },
        {
            "id": "61569338451417",
            "count": 0
        },
        {
            "id": "61563496809381",
            "count": 78
        },
        {
            "id": "61577050643994",
            "count": 0
        },
        {
            "id": "100091313000090",
            "count": 0
        },
        {
            "id": "100068861768111",
            "count": 0
        },
        {
            "id": "100080152698087",
            "count": 0
        },
        {
            "id": "100090518522825",
            "count": 0
        },
        {
            "id": "61569795707805",
            "count": 0
        },
        {
            "id": "61557751285756",
            "count": 0
        },
        {
            "id": "61563801070353",
            "count": 0
        },
        {
            "id": "61550807512404",
            "count": 0
        },
        {
            "id": "61556139488045",
            "count": 0
        },
        {
            "id": "61550951499471",
            "count": 0
        },
        {
            "id": "100003400690051",
            "count": 0
        },
        {
            "id": "100086620849345",
            "count": 0
        },
        {
            "id": "100091769754934",
            "count": 0
        },
        {
            "id": "61562564625370",
            "count": 0
        },
        {
            "id": "100075476904971",
            "count": 0
        },
        {
            "id": "61554085977198",
            "count": 0
        },
        {
            "id": "61576303087087",
            "count": 0
        },
        {
            "id": "100090183633143",
            "count": 0
        },
        {
            "id": "100064900510879",
            "count": 0
        },
        {
            "id": "100088856464252",
            "count": 0
        },
        {
            "id": "100064836047753",
            "count": 0
        },
        {
            "id": "100075241353285",
            "count": 7
        },
        {
            "id": "100093035131692",
            "count": 2
        },
        {
            "id": "61555812975932",
            "count": 0
        },
        {
            "id": "61555315402231",
            "count": 26
        },
        {
            "id": "100067074994636",
            "count": 4
        },
        {
            "id": "100016721569402",
            "count": 0
        },
        {
            "id": "100072621417020",
            "count": 0
        },
        {
            "id": "100036907965091",
            "count": 0
        },
        {
            "id": "100078738729314",
            "count": 0
        },
        {
            "id": "61576808576607",
            "count": 0
        },
        {
            "id": "61566315946205",
            "count": 0
        },
        {
            "id": "61573134763751",
            "count": 0
        },
        {
            "id": "100094266671898",
            "count": 0
        },
        {
            "id": "100091827653492",
            "count": 0
        },
        {
            "id": "100069413591161",
            "count": 2
        },
        {
            "id": "61571179656820",
            "count": 0
        },
        {
            "id": "100084053954585",
            "count": 0
        },
        {
            "id": "61565926051279",
            "count": 0
        },
        {
            "id": "61575653644435",
            "count": 0
        },
        {
            "id": "61559687282718",
            "count": 0
        },
        {
            "id": "100093260420505",
            "count": 0
        },
        {
            "id": "100088184953277",
            "count": 0
        },
        {
            "id": "100046491823260",
            "count": 0
        },
        {
            "id": "61551598754384",
            "count": 0
        },
        {
            "id": "100078074537976",
            "count": 0
        },
        {
            "id": "61576748741913",
            "count": 0
        },
        {
            "id": "61565416546012",
            "count": 0
        },
        {
            "id": "61572605409468",
            "count": 0
        },
        {
            "id": "100089484682790",
            "count": 0
        },
        {
            "id": "61563816474622",
            "count": 0
        },
        {
            "id": "100054238185744",
            "count": 0
        },
        {
            "id": "100087502185841",
            "count": 0
        },
        {
            "id": "100023417120542",
            "count": 3
        },
        {
            "id": "100080987002074",
            "count": 0
        },
        {
            "id": "100061767325182",
            "count": 1
        },
        {
            "id": "100052091616457",
            "count": 0
        },
        {
            "id": "61570942973518",
            "count": 0
        },
        {
            "id": "100095167591736",
            "count": 5
        },
        {
            "id": "61563371807835",
            "count": 0
        },
        {
            "id": "61572794682692",
            "count": 0
        },
        {
            "id": "100049794199395",
            "count": 0
        },
        {
            "id": "1159830790",
            "count": 0
        },
        {
            "id": "100076389226937",
            "count": 0
        },
        {
            "id": "61557186861552",
            "count": 0
        },
        {
            "id": "100076319085100",
            "count": 14
        },
        {
            "id": "61575275421167",
            "count": 0
        },
        {
            "id": "100093316167658",
            "count": 0
        },
        {
            "id": "61568101333346",
            "count": 0
        },
        {
            "id": "61567137231981",
            "count": 12
        },
        {
            "id": "61556420127089",
            "count": 0
        },
        {
            "id": "100095460641478",
            "count": 0
        },
        {
            "id": "61568278007683",
            "count": 73
        },
        {
            "id": "61564167278498",
            "count": 35
        },
        {
            "id": "100027455436738",
            "count": 0
        },
        {
            "id": "100082900982212",
            "count": 0
        },
        {
            "id": "100094512588578",
            "count": 0
        },
        {
            "id": "61572591704444",
            "count": 0
        },
        {
            "id": "100060204365790",
            "count": 0
        },
        {
            "id": "100074496522992",
            "count": 0
        },
        {
            "id": "61576283133154",
            "count": 0
        },
        {
            "id": "100094054120969",
            "count": 3
        },
        {
            "id": "100087347266718",
            "count": 0
        },
        {
            "id": "61550856910712",
            "count": 0
        },
        {
            "id": "100049598619114",
            "count": 0
        },
        {
            "id": "100024191822441",
            "count": 0
        },
        {
            "id": "100072570150185",
            "count": 0
        },
        {
            "id": "61571018824787",
            "count": 0
        },
        {
            "id": "100091887677635",
            "count": 0
        },
        {
            "id": "61559795476222",
            "count": 0
        },
        {
            "id": "61550974984898",
            "count": 0
        },
        {
            "id": "61558254400327",
            "count": 0
        },
        {
            "id": "61577376624706",
            "count": 0
        },
        {
            "id": "61558260482380",
            "count": 0
        },
        {
            "id": "61575080083211",
            "count": 0
        },
        {
            "id": "706632570",
            "count": 0
        },
        {
            "id": "100077086391543",
            "count": 0
        },
        {
            "id": "61564917430103",
            "count": 0
        },
        {
            "id": "61574897218707",
            "count": 104
        },
        {
            "id": "61577384667474",
            "count": 0
        },
        {
            "id": "61577399547420",
            "count": 0
        },
        {
            "id": "100068760339372",
            "count": 0
        },
        {
            "id": "61575964492920",
            "count": 0
        },
        {
            "id": "61554796626113",
            "count": 0
        },
        {
            "id": "61565430903608",
            "count": 0
        },
        {
            "id": "61566324585655",
            "count": 0
        },
        {
            "id": "61563081494832",
            "count": 9
        },
        {
            "id": "61563338433154",
            "count": 0
        },
        {
            "id": "61577350772075",
            "count": 0
        },
        {
            "id": "100041071671685",
            "count": 1
        },
        {
            "id": "61574196725988",
            "count": 0
        },
        {
            "id": "61566302851089",
            "count": 1
        },
        {
            "id": "100004204689863",
            "count": 0
        },
        {
            "id": "100080665522298",
            "count": 0
        },
        {
            "id": "61571461029115",
            "count": 0
        },
        {
            "id": "61555109330415",
            "count": 0
        },
        {
            "id": "61554427572388",
            "count": 0
        },
        {
            "id": "61573176244352",
            "count": 0
        },
        {
            "id": "100001664242548",
            "count": 0
        },
        {
            "id": "100079781445543",
            "count": 0
        },
        {
            "id": "61577473147128",
            "count": 0
        },
        {
            "id": "61559388620470",
            "count": 0
        },
        {
            "id": "100050335652391",
            "count": 0
        },
        {
            "id": "61576322793220",
            "count": 2
        },
        {
            "id": "61560437371885",
            "count": 0
        },
        {
            "id": "100079756907572",
            "count": 0
        },
        {
            "id": "61575619948093",
            "count": 0
        },
        {
            "id": "61570064048722",
            "count": 0
        },
        {
            "id": "61576593236518",
            "count": 0
        },
        {
            "id": "61572692185146",
            "count": 0
        },
        {
            "id": "61573015991517",
            "count": 0
        },
        {
            "id": "61577338381895",
            "count": 0
        },
        {
            "id": "61573057942187",
            "count": 5
        },
        {
            "id": "100054255814951",
            "count": 0
        },
        {
            "id": "61575859743375",
            "count": 2
        },
        {
            "id": "61556365787922",
            "count": 35
        },
        {
            "id": "61570065247432",
            "count": 0
        },
        {
            "id": "61567036355819",
            "count": 0
        },
        {
            "id": "100089877112021",
            "count": 0
        },
        {
            "id": "61561301781412",
            "count": 0
        },
        {
            "id": "61569508901773",
            "count": 0
        },
        {
            "id": "100095363102708",
            "count": 0
        },
        {
            "id": "61555318124009",
            "count": 2
        },
        {
            "id": "100072003416462",
            "count": 23
        },
        {
            "id": "61577324252460",
            "count": 13
        },
        {
            "id": "100075416601396",
            "count": 12
        },
        {
            "id": "100093017079432",
            "count": 1
        },
        {
            "id": "100033622700609",
            "count": 87
        },
        {
            "id": "61559800701404",
            "count": 9
        },
        {
            "id": "100054549946196",
            "count": 0
        },
        {
            "id": "61573785396957",
            "count": 15
        },
        {
            "id": "100073454930514",
            "count": 0
        },
        {
            "id": "100071847031894",
            "count": 0
        },
        {
            "id": "61576818456790",
            "count": 0
        },
        {
            "id": "100051958717970",
            "count": 37
        },
        {
            "id": "61577423374306",
            "count": 5
        },
        {
            "id": "61567376367950",
            "count": 0
        },
        {
            "id": "61577774257596",
            "count": 2
        },
        {
            "id": "61556472763954",
            "count": 0
        },
        {
            "id": "61573424942469",
            "count": 1
        }
    ],
    "time": 2,
    "last": {
        "time": 0,
        "day": [
            {
                "id": "100004366982560",
                "count": 0
            },
            {
                "id": "61569338451417",
                "count": 0
            },
            {
                "id": "61563496809381",
                "count": 0
            },
            {
                "id": "61577050643994",
                "count": 0
            },
            {
                "id": "100091313000090",
                "count": 0
            },
            {
                "id": "100068861768111",
                "count": 0
            },
            {
                "id": "100080152698087",
                "count": 0
            },
            {
                "id": "100090518522825",
                "count": 0
            },
            {
                "id": "61569795707805",
                "count": 0
            },
            {
                "id": "61557751285756",
                "count": 0
            },
            {
                "id": "61563801070353",
                "count": 0
            },
            {
                "id": "61550807512404",
                "count": 0
            },
            {
                "id": "61556139488045",
                "count": 0
            },
            {
                "id": "61550951499471",
                "count": 0
            },
            {
                "id": "100003400690051",
                "count": 0
            },
            {
                "id": "100086620849345",
                "count": 0
            },
            {
                "id": "100091769754934",
                "count": 0
            },
            {
                "id": "61562564625370",
                "count": 0
            },
            {
                "id": "100075476904971",
                "count": 0
            },
            {
                "id": "61554085977198",
                "count": 0
            },
            {
                "id": "61576303087087",
                "count": 0
            },
            {
                "id": "100090183633143",
                "count": 0
            },
            {
                "id": "100064900510879",
                "count": 0
            },
            {
                "id": "100088856464252",
                "count": 0
            },
            {
                "id": "100064836047753",
                "count": 0
            },
            {
                "id": "100075241353285",
                "count": 0
            },
            {
                "id": "100093035131692",
                "count": 0
            },
            {
                "id": "61555812975932",
                "count": 0
            },
            {
                "id": "61555315402231",
                "count": 0
            },
            {
                "id": "100067074994636",
                "count": 0
            },
            {
                "id": "100016721569402",
                "count": 0
            },
            {
                "id": "100072621417020",
                "count": 0
            },
            {
                "id": "100036907965091",
                "count": 0
            },
            {
                "id": "100078738729314",
                "count": 0
            },
            {
                "id": "61576808576607",
                "count": 0
            },
            {
                "id": "61566315946205",
                "count": 0
            },
            {
                "id": "61573134763751",
                "count": 0
            },
            {
                "id": "100094266671898",
                "count": 0
            },
            {
                "id": "100091827653492",
                "count": 0
            },
            {
                "id": "100069413591161",
                "count": 0
            },
            {
                "id": "61571179656820",
                "count": 0
            },
            {
                "id": "100084053954585",
                "count": 0
            },
            {
                "id": "61565926051279",
                "count": 0
            },
            {
                "id": "61575653644435",
                "count": 0
            },
            {
                "id": "61559687282718",
                "count": 0
            },
            {
                "id": "100093260420505",
                "count": 0
            },
            {
                "id": "100088184953277",
                "count": 0
            },
            {
                "id": "100046491823260",
                "count": 0
            },
            {
                "id": "61551598754384",
                "count": 0
            },
            {
                "id": "100078074537976",
                "count": 0
            },
            {
                "id": "61576748741913",
                "count": 0
            },
            {
                "id": "61565416546012",
                "count": 0
            },
            {
                "id": "61572605409468",
                "count": 0
            },
            {
                "id": "100089484682790",
                "count": 0
            },
            {
                "id": "61563816474622",
                "count": 0
            },
            {
                "id": "100054238185744",
                "count": 0
            },
            {
                "id": "100087502185841",
                "count": 0
            },
            {
                "id": "100023417120542",
                "count": 0
            },
            {
                "id": "100080987002074",
                "count": 0
            },
            {
                "id": "100061767325182",
                "count": 0
            },
            {
                "id": "100052091616457",
                "count": 0
            },
            {
                "id": "61570942973518",
                "count": 0
            },
            {
                "id": "100095167591736",
                "count": 0
            },
            {
                "id": "61563371807835",
                "count": 0
            },
            {
                "id": "61572794682692",
                "count": 0
            },
            {
                "id": "100049794199395",
                "count": 0
            },
            {
                "id": "1159830790",
                "count": 0
            },
            {
                "id": "100076389226937",
                "count": 0
            },
            {
                "id": "61557186861552",
                "count": 0
            },
            {
                "id": "100076319085100",
                "count": 0
            },
            {
                "id": "61575275421167",
                "count": 0
            },
            {
                "id": "100093316167658",
                "count": 0
            },
            {
                "id": "61568101333346",
                "count": 0
            },
            {
                "id": "61567137231981",
                "count": 0
            },
            {
                "id": "61556420127089",
                "count": 0
            },
            {
                "id": "100095460641478",
                "count": 0
            },
            {
                "id": "61568278007683",
                "count": 0
            },
            {
                "id": "61564167278498",
                "count": 0
            },
            {
                "id": "100027455436738",
                "count": 0
            },
            {
                "id": "100082900982212",
                "count": 0
            },
            {
                "id": "100094512588578",
                "count": 0
            },
            {
                "id": "61572591704444",
                "count": 0
            },
            {
                "id": "100060204365790",
                "count": 0
            },
            {
                "id": "100074496522992",
                "count": 0
            },
            {
                "id": "61576283133154",
                "count": 0
            },
            {
                "id": "100094054120969",
                "count": 0
            },
            {
                "id": "100087347266718",
                "count": 0
            },
            {
                "id": "61550856910712",
                "count": 0
            },
            {
                "id": "100049598619114",
                "count": 0
            },
            {
                "id": "100024191822441",
                "count": 0
            },
            {
                "id": "100072570150185",
                "count": 0
            },
            {
                "id": "61571018824787",
                "count": 0
            },
            {
                "id": "100091887677635",
                "count": 0
            },
            {
                "id": "61559795476222",
                "count": 0
            },
            {
                "id": "61550974984898",
                "count": 0
            },
            {
                "id": "61558254400327",
                "count": 0
            },
            {
                "id": "61577376624706",
                "count": 0
            },
            {
                "id": "61558260482380",
                "count": 0
            },
            {
                "id": "61575080083211",
                "count": 0
            },
            {
                "id": "706632570",
                "count": 0
            },
            {
                "id": "100077086391543",
                "count": 0
            },
            {
                "id": "100044706315105",
                "count": 0
            },
            {
                "id": "61564917430103",
                "count": 0
            },
            {
                "id": "61574897218707",
                "count": 0
            },
            {
                "id": "61577384667474",
                "count": 0
            },
            {
                "id": "61577399547420",
                "count": 0
            },
            {
                "id": "100068760339372",
                "count": 0
            },
            {
                "id": "61575964492920",
                "count": 0
            },
            {
                "id": "61554796626113",
                "count": 0
            },
            {
                "id": "61565430903608",
                "count": 0
            },
            {
                "id": "61566324585655",
                "count": 0
            },
            {
                "id": "61563081494832",
                "count": 0
            },
            {
                "id": "61563338433154",
                "count": 0
            },
            {
                "id": "61577350772075",
                "count": 0
            },
            {
                "id": "100041071671685",
                "count": 0
            },
            {
                "id": "61574196725988",
                "count": 0
            },
            {
                "id": "61566302851089",
                "count": 0
            },
            {
                "id": "100004204689863",
                "count": 0
            },
            {
                "id": "100080665522298",
                "count": 0
            },
            {
                "id": "61571461029115",
                "count": 0
            },
            {
                "id": "61555109330415",
                "count": 0
            },
            {
                "id": "61554427572388",
                "count": 0
            },
            {
                "id": "61573176244352",
                "count": 0
            },
            {
                "id": "100001664242548",
                "count": 0
            },
            {
                "id": "100079781445543",
                "count": 0
            },
            {
                "id": "61577473147128",
                "count": 0
            },
            {
                "id": "61559388620470",
                "count": 0
            },
            {
                "id": "100050335652391",
                "count": 0
            },
            {
                "id": "100094148499855",
                "count": 0
            },
            {
                "id": "61576322793220",
                "count": 0
            },
            {
                "id": "61560437371885",
                "count": 0
            },
            {
                "id": "100079756907572",
                "count": 0
            },
            {
                "id": "61575619948093",
                "count": 0
            },
            {
                "id": "61570064048722",
                "count": 0
            },
            {
                "id": "61576593236518",
                "count": 0
            },
            {
                "id": "61572692185146",
                "count": 0
            },
            {
                "id": "61573015991517",
                "count": 0
            },
            {
                "id": "61577338381895",
                "count": 0
            },
            {
                "id": "61573057942187",
                "count": 0
            },
            {
                "id": "100054255814951",
                "count": 0
            },
            {
                "id": "61575859743375",
                "count": 0
            },
            {
                "id": "61556365787922",
                "count": 0
            },
            {
                "id": "61570065247432",
                "count": 0
            },
            {
                "id": "61567036355819",
                "count": 0
            },
            {
                "id": "100089877112021",
                "count": 0
            },
            {
                "id": "61561301781412",
                "count": 0
            },
            {
                "id": "61569508901773",
                "count": 0
            },
            {
                "id": "100095363102708",
                "count": 0
            },
            {
                "id": "61555318124009",
                "count": 0
            },
            {
                "id": "100072003416462",
                "count": 0
            },
            {
                "id": "61577324252460",
                "count": 0
            },
            {
                "id": "100075416601396",
                "count": 0
            },
            {
                "id": "100093017079432",
                "count": 0
            },
            {
                "id": "100033622700609",
                "count": 0
            },
            {
                "id": "61559800701404",
                "count": 0
            },
            {
                "id": "100054549946196",
                "count": 0
            },
            {
                "id": "61573785396957",
                "count": 0
            },
            {
                "id": "100073454930514",
                "count": 0
            },
            {
                "id": "100071847031894",
                "count": 0
            },
            {
                "id": "61576818456790",
                "count": 0
            },
            {
                "id": "100051958717970",
                "count": 0
            },
            {
                "id": "61577423374306",
                "count": 0
            },
            {
                "id": "61578035573431",
                "count": 0
            },
            {
                "id": "61567376367950",
                "count": 0
            },
            {
                "id": "61577774257596",
                "count": 0
            },
            {
                "id": "61556472763954",
                "count": 0
            },
            {
                "id": "61573424942469",
                "count": 0
            }
        ],
        "week": [
            {
                "id": "100004366982560",
                "count": 0
            },
            {
                "id": "61569338451417",
                "count": 0
            },
            {
                "id": "61563496809381",
                "count": 0
            },
            {
                "id": "61577050643994",
                "count": 0
            },
            {
                "id": "100091313000090",
                "count": 0
            },
            {
                "id": "100068861768111",
                "count": 0
            },
            {
                "id": "100080152698087",
                "count": 0
            },
            {
                "id": "100090518522825",
                "count": 0
            },
            {
                "id": "61569795707805",
                "count": 0
            },
            {
                "id": "61557751285756",
                "count": 0
            },
            {
                "id": "61563801070353",
                "count": 0
            },
            {
                "id": "61550807512404",
                "count": 0
            },
            {
                "id": "61556139488045",
                "count": 0
            },
            {
                "id": "61550951499471",
                "count": 0
            },
            {
                "id": "100003400690051",
                "count": 0
            },
            {
                "id": "100086620849345",
                "count": 0
            },
            {
                "id": "100091769754934",
                "count": 0
            },
            {
                "id": "61562564625370",
                "count": 0
            },
            {
                "id": "100075476904971",
                "count": 0
            },
            {
                "id": "61554085977198",
                "count": 0
            },
            {
                "id": "61576303087087",
                "count": 0
            },
            {
                "id": "100090183633143",
                "count": 0
            },
            {
                "id": "100064900510879",
                "count": 0
            },
            {
                "id": "100088856464252",
                "count": 0
            },
            {
                "id": "100064836047753",
                "count": 0
            },
            {
                "id": "100075241353285",
                "count": 0
            },
            {
                "id": "100093035131692",
                "count": 0
            },
            {
                "id": "61555812975932",
                "count": 0
            },
            {
                "id": "61555315402231",
                "count": 0
            },
            {
                "id": "100067074994636",
                "count": 0
            },
            {
                "id": "100016721569402",
                "count": 0
            },
            {
                "id": "100072621417020",
                "count": 0
            },
            {
                "id": "100036907965091",
                "count": 0
            },
            {
                "id": "100078738729314",
                "count": 0
            },
            {
                "id": "61576808576607",
                "count": 0
            },
            {
                "id": "61566315946205",
                "count": 0
            },
            {
                "id": "61573134763751",
                "count": 0
            },
            {
                "id": "100094266671898",
                "count": 0
            },
            {
                "id": "100091827653492",
                "count": 0
            },
            {
                "id": "100069413591161",
                "count": 0
            },
            {
                "id": "61571179656820",
                "count": 0
            },
            {
                "id": "100084053954585",
                "count": 0
            },
            {
                "id": "61565926051279",
                "count": 0
            },
            {
                "id": "61575653644435",
                "count": 0
            },
            {
                "id": "61559687282718",
                "count": 0
            },
            {
                "id": "100093260420505",
                "count": 0
            },
            {
                "id": "100088184953277",
                "count": 0
            },
            {
                "id": "100046491823260",
                "count": 0
            },
            {
                "id": "61551598754384",
                "count": 0
            },
            {
                "id": "100078074537976",
                "count": 0
            },
            {
                "id": "61576748741913",
                "count": 0
            },
            {
                "id": "61565416546012",
                "count": 0
            },
            {
                "id": "61572605409468",
                "count": 0
            },
            {
                "id": "100089484682790",
                "count": 0
            },
            {
                "id": "61563816474622",
                "count": 0
            },
            {
                "id": "100054238185744",
                "count": 0
            },
            {
                "id": "100087502185841",
                "count": 0
            },
            {
                "id": "100023417120542",
                "count": 0
            },
            {
                "id": "100080987002074",
                "count": 0
            },
            {
                "id": "100061767325182",
                "count": 0
            },
            {
                "id": "100052091616457",
                "count": 0
            },
            {
                "id": "61570942973518",
                "count": 0
            },
            {
                "id": "100095167591736",
                "count": 0
            },
            {
                "id": "61563371807835",
                "count": 0
            },
            {
                "id": "61572794682692",
                "count": 0
            },
            {
                "id": "100049794199395",
                "count": 0
            },
            {
                "id": "1159830790",
                "count": 0
            },
            {
                "id": "100076389226937",
                "count": 0
            },
            {
                "id": "61557186861552",
                "count": 0
            },
            {
                "id": "100076319085100",
                "count": 0
            },
            {
                "id": "61575275421167",
                "count": 0
            },
            {
                "id": "100093316167658",
                "count": 0
            },
            {
                "id": "61568101333346",
                "count": 0
            },
            {
                "id": "61567137231981",
                "count": 0
            },
            {
                "id": "61556420127089",
                "count": 0
            },
            {
                "id": "100095460641478",
                "count": 0
            },
            {
                "id": "61568278007683",
                "count": 0
            },
            {
                "id": "61564167278498",
                "count": 0
            },
            {
                "id": "100027455436738",
                "count": 0
            },
            {
                "id": "100082900982212",
                "count": 0
            },
            {
                "id": "100094512588578",
                "count": 0
            },
            {
                "id": "61572591704444",
                "count": 0
            },
            {
                "id": "100060204365790",
                "count": 0
            },
            {
                "id": "100074496522992",
                "count": 0
            },
            {
                "id": "61576283133154",
                "count": 0
            },
            {
                "id": "100094054120969",
                "count": 0
            },
            {
                "id": "100087347266718",
                "count": 0
            },
            {
                "id": "61550856910712",
                "count": 0
            },
            {
                "id": "100049598619114",
                "count": 0
            },
            {
                "id": "100024191822441",
                "count": 0
            },
            {
                "id": "100072570150185",
                "count": 0
            },
            {
                "id": "61571018824787",
                "count": 0
            },
            {
                "id": "100091887677635",
                "count": 0
            },
            {
                "id": "61559795476222",
                "count": 0
            },
            {
                "id": "61550974984898",
                "count": 0
            },
            {
                "id": "61558254400327",
                "count": 0
            },
            {
                "id": "61577376624706",
                "count": 0
            },
            {
                "id": "61558260482380",
                "count": 0
            },
            {
                "id": "61575080083211",
                "count": 0
            },
            {
                "id": "706632570",
                "count": 0
            },
            {
                "id": "100077086391543",
                "count": 0
            },
            {
                "id": "100044706315105",
                "count": 0
            },
            {
                "id": "61564917430103",
                "count": 0
            },
            {
                "id": "61574897218707",
                "count": 0
            },
            {
                "id": "61577384667474",
                "count": 0
            },
            {
                "id": "61577399547420",
                "count": 0
            },
            {
                "id": "100068760339372",
                "count": 0
            },
            {
                "id": "61575964492920",
                "count": 0
            },
            {
                "id": "61554796626113",
                "count": 0
            },
            {
                "id": "61565430903608",
                "count": 0
            },
            {
                "id": "61566324585655",
                "count": 0
            },
            {
                "id": "61563081494832",
                "count": 0
            },
            {
                "id": "61563338433154",
                "count": 0
            },
            {
                "id": "61577350772075",
                "count": 0
            },
            {
                "id": "100041071671685",
                "count": 0
            },
            {
                "id": "61574196725988",
                "count": 0
            },
            {
                "id": "61566302851089",
                "count": 0
            },
            {
                "id": "100004204689863",
                "count": 0
            },
            {
                "id": "100080665522298",
                "count": 0
            },
            {
                "id": "61571461029115",
                "count": 0
            },
            {
                "id": "61555109330415",
                "count": 0
            },
            {
                "id": "61554427572388",
                "count": 0
            },
            {
                "id": "61573176244352",
                "count": 0
            },
            {
                "id": "100001664242548",
                "count": 0
            },
            {
                "id": "100079781445543",
                "count": 0
            },
            {
                "id": "61577473147128",
                "count": 0
            },
            {
                "id": "61559388620470",
                "count": 0
            },
            {
                "id": "100050335652391",
                "count": 0
            },
            {
                "id": "100094148499855",
                "count": 0
            },
            {
                "id": "61576322793220",
                "count": 0
            },
            {
                "id": "61560437371885",
                "count": 0
            },
            {
                "id": "100079756907572",
                "count": 0
            },
            {
                "id": "61575619948093",
                "count": 0
            },
            {
                "id": "61570064048722",
                "count": 0
            },
            {
                "id": "61576593236518",
                "count": 0
            },
            {
                "id": "61572692185146",
                "count": 0
            },
            {
                "id": "61573015991517",
                "count": 0
            },
            {
                "id": "61577338381895",
                "count": 0
            },
            {
                "id": "61573057942187",
                "count": 0
            },
            {
                "id": "100054255814951",
                "count": 0
            },
            {
                "id": "61575859743375",
                "count": 0
            },
            {
                "id": "61556365787922",
                "count": 0
            },
            {
                "id": "61570065247432",
                "count": 0
            },
            {
                "id": "61567036355819",
                "count": 0
            },
            {
                "id": "100089877112021",
                "count": 0
            },
            {
                "id": "61561301781412",
                "count": 0
            },
            {
                "id": "61569508901773",
                "count": 0
            },
            {
                "id": "100095363102708",
                "count": 0
            },
            {
                "id": "61555318124009",
                "count": 0
            },
            {
                "id": "100072003416462",
                "count": 0
            },
            {
                "id": "61577324252460",
                "count": 0
            },
            {
                "id": "100075416601396",
                "count": 0
            },
            {
                "id": "100093017079432",
                "count": 0
            },
            {
                "id": "100033622700609",
                "count": 0
            },
            {
                "id": "61559800701404",
                "count": 0
            },
            {
                "id": "100054549946196",
                "count": 0
            },
            {
                "id": "61573785396957",
                "count": 0
            },
            {
                "id": "100073454930514",
                "count": 0
            },
            {
                "id": "100071847031894",
                "count": 0
            },
            {
                "id": "61576818456790",
                "count": 0
            },
            {
                "id": "100051958717970",
                "count": 0
            },
            {
                "id": "61577423374306",
                "count": 0
            },
            {
                "id": "61578035573431",
                "count": 0
            },
            {
                "id": "61567376367950",
                "count": 0
            },
            {
                "id": "61577774257596",
                "count": 0
            },
            {
                "id": "61556472763954",
                "count": 0
            },
            {
                "id": "61573424942469",
                "count": 0
            }
        ]
    },
    "lastInteraction": {
        "61563081494832": 1751210487261,
        "61556365787922": 1751292538010,
        "61563496809381": 1751276294428,
        "61568278007683": 1751293390823,
        "100095167591736": 1751213389512,
        "100067074994636": 1751294234674,
        "61564167278498": 1751287660571,
        "61573785396957": 1751271765615,
        "100051958717970": 1751286513976,
        "61577324252460": 1751273301928,
        "100072003416462": 1751272974131,
        "100094054120969": 1751255401223,
        "100041071671685": 1751218008757,
        "61559800701404": 1751287674165,
        "100075241353285": 1751286428117,
        "100061767325182": 1751228967787,
        "61567137231981": 1751229987069,
        "61574897218707": 1751287212883,
        "100093035131692": 1751255564707,
        "61566302851089": 1751236970101,
        "100033622700609": 1751292897885,
        "61573057942187": 1751270174851,
        "61576322793220": 1751254658239,
        "61575859743375": 1751255235535,
        "100069413591161": 1751261284875,
        "61555318124009": 1751292854838,
        "61555315402231": 1751293482401,
        "100076319085100": 1751275390130,
        "61577774257596": 1751276898396,
        "100023417120542": 1751293789166,
        "61573424942469": 1751283756540,
        "100075416601396": 1751284372118,
        "100093017079432": 1751284028961,
        "61577423374306": 1751285155757
    }
}